wackyurls/__init__.py
wackyurls/data/adjectives.txt
wackyurls/data/nouns.txt
wackyurls-0.1.dist-info/METADATA
wackyurls-0.1.dist-info/WHEEL
wackyurls-0.1.dist-info/top_level.txt
wackyurls-0.1.dist-info/RECORD
