Metadata-Version: 2.1
Name: wackyurls
Version: 0.1
Summary: Generates random URLs from nouns and adjectives.
Home-page: UNKNOWN
Author: briccardo
Author-email: rbiagini02@gmail.com
License: MIT
Platform: UNKNOWN
Classifier: License :: OSI Approved :: MIT License
Classifier: Programming Language :: Python :: 3.8
